fluxon/__init__.py
fluxon/format_converter.py
fluxon/parser.py
fluxon/prompter.py
fluxon/utils.py
fluxon/validator.py
fluxon-0.0.3.dist-info/LICENSE
fluxon-0.0.3.dist-info/METADATA
fluxon-0.0.3.dist-info/WHEEL
fluxon-0.0.3.dist-info/top_level.txt
fluxon-0.0.3.dist-info/RECORD
