Metadata-Version: 2.1
Name: fluxon
Version: 0.0.3
Summary: A Python library for crafting structured prompts and parsing structured outputs with a focus on JSON.
Home-page: https://github.com/ymitiku/fluxon
Author: Mitiku Yohannes
Author-email: se.mitiku.yohannes@gmail.com
Classifier: Programming Language :: Python :: 3
Classifier: License :: OSI Approved :: Apache Software License
Classifier: Operating System :: OS Independent
Requires-Python: >=3.10
License-File: LICENSE
Requires-Dist: jsonschema>=4.0.0
Requires-Dist: pydantic>=1.10.0
Provides-Extra: dev
Requires-Dist: pytest>=7.0; extra == "dev"
Requires-Dist: black>=22.0; extra == "dev"
Requires-Dist: flake8>=4.0; extra == "dev"
